CHANGES.txt
README.txt
buildout.cfg
setup.py
versions.cfg
src/zc/__init__.py
src/zc.ajaxform.egg-info/PKG-INFO
src/zc.ajaxform.egg-info/SOURCES.txt
src/zc.ajaxform.egg-info/dependency_links.txt
src/zc.ajaxform.egg-info/entry_points.txt
src/zc.ajaxform.egg-info/namespace_packages.txt
src/zc.ajaxform.egg-info/not-zip-safe
src/zc.ajaxform.egg-info/requires.txt
src/zc.ajaxform.egg-info/top_level.txt
src/zc/ajaxform/README.txt
src/zc/ajaxform/__init__.py
src/zc/ajaxform/application.py
src/zc/ajaxform/application.txt
src/zc/ajaxform/calculator_example.py
src/zc/ajaxform/calculator_example.zcml
src/zc/ajaxform/calculator_subapplication_example.py
src/zc/ajaxform/calculator_subapplication_example.zcml
src/zc/ajaxform/configure.zcml
src/zc/ajaxform/form.py
src/zc/ajaxform/form.test
src/zc/ajaxform/form_example.py
src/zc/ajaxform/form_example.zcml
src/zc/ajaxform/interfaces.py
src/zc/ajaxform/session.py
src/zc/ajaxform/session.txt
src/zc/ajaxform/session.zcml
src/zc/ajaxform/testing.py
src/zc/ajaxform/tests.py
src/zc/ajaxform/tests.zcml
src/zc/ajaxform/widgets.py
src/zc/ajaxform/widgets.txt
src/zc/ajaxform/widgets.zcml