Metadata-Version: 1.0
Name: zc.ajaxform
Version: 0.7.0
Summary: UNKNOWN
Home-page: UNKNOWN
Author: Jim Fulton
Author-email: jim@zope.com
License: ZPL 2.1
Platform: UNKNOWN
